Metadata-Version: 2.4
Name: polars-hash-lts-cpu
Version: 0.5.5
Classifier: Programming Language :: Rust
Classifier: Programming Language :: Python :: Implementation :: CPython
Classifier: Programming Language :: Python :: Implementation :: PyPy
Requires-Dist: polars-lts-cpu>=1.33.0
Summary: Stable non-cryptographic and cryptographic hashing functions for Polars
Author-email: Ion Koutsours <15728914+ion-elgreco@users.noreply.github.com>
Requires-Python: >=3.10
Project-URL: Homepage, https://github.com/milaboratory/polars-hash-lts-cpu
Project-URL: Bug Tracker, https://github.com/milaboratory/platforma/issues
